rplidarc1/__init__.py
rplidarc1/examples/__init__.py
rplidarc1/examples/run.py
rplidarc1/protocol.py
rplidarc1/scanner.py
rplidarc1/serial_handler.py
rplidarc1/utils.py
rplidarc1-0.1.3.dist-info/METADATA
rplidarc1-0.1.3.dist-info/WHEEL
rplidarc1-0.1.3.dist-info/RECORD
