Metadata-Version: 2.3
Name: rplidarc1
Version: 0.1.3
Summary: Asynchronous Python library for RPLidar C1 laser scanners with robust data handling, error recovery, and minimal dependencies (pyserial only). Designed for efficient robotics and sensing applications.
License: MIT
Author: David Milad Saadatmandi
Author-email: davidmilad@gmail.com
Requires-Python: >=3.10
Classifier: License :: OSI Approved :: MIT License
Classifier: Programming Language :: Python :: 3
Classifier: Programming Language :: Python :: 3.10
Classifier: Programming Language :: Python :: 3.11
Classifier: Programming Language :: Python :: 3.12
Classifier: Programming Language :: Python :: 3.13
Requires-Dist: pyserial (>=3.5)
